Aiology/__init__.py
Aiology/main.py
aiology-0.4.dist-info/METADATA
aiology-0.4.dist-info/WHEEL
aiology-0.4.dist-info/top_level.txt
aiology-0.4.dist-info/RECORD
