Metadata-Version: 2.4
Name: Aiology
Version: 0.4
Author: Seyed Moied Seyedi (Single Star)
Dynamic: author
Dynamic: description
Dynamic: description-content-type
